[
  {
    "id": "07234a94-f4c1-4999-a53c-6c5159609e80",
    "name": "fahi",
    "number": "+225 0787093607",
    "email": "wilfried.konan@epitech.eu",
    "message": "fbd",
    "timestamp": "2025-04-02T09:11:06.722Z"
  },
  {
    "id": "fe5024d2-883a-4ca8-ac79-305a3387fe63",
    "name": "Ganfon",
    "number": "+225 0787093607",
    "email": "wil787@gmail.com",
    "message": "le message",
    "timestamp": "2025-04-03T18:10:00.272Z"
  },
  {
    "id": "e16a1450-507f-4b3b-8b3b-f5dd9277e237",
    "name": "Cheick",
    "number": "+225 0787093607",
    "email": "wil787@gmail.com",
    "message": "test",
    "timestamp": "2025-04-17T13:11:03.139Z"
  }
]